findssh/__init__.py
findssh/__main__.py
findssh/base.py
findssh/coro.py
findssh/threadpool.py
findssh/tests/__init__.py
findssh/tests/test_coro.py
findssh/tests/test_threadpool.py
findssh-2.0.1.dist-info/LICENSE.txt
findssh-2.0.1.dist-info/METADATA
findssh-2.0.1.dist-info/WHEEL
findssh-2.0.1.dist-info/entry_points.txt
findssh-2.0.1.dist-info/top_level.txt
findssh-2.0.1.dist-info/RECORD
